pysmoove_summary/__init__.py
pysmoove_summary/correlated_phenotypes.py
pysmoove_summary/correlated_phenotypes_3rdseq.py
pysmoove_summary/parse_phenotypes.py
pysmoove_summary/parse_phenotypes_3rdseq.py
pysmoove_summary/pysmoove_summary.py
pysmoove_summary-0.0.6.dist-info/LICENSE
pysmoove_summary-0.0.6.dist-info/METADATA
pysmoove_summary-0.0.6.dist-info/WHEEL
pysmoove_summary-0.0.6.dist-info/entry_points.txt
pysmoove_summary-0.0.6.dist-info/top_level.txt
pysmoove_summary-0.0.6.dist-info/RECORD
