Metadata-Version: 2.1
Name: pysmoove-summary
Version: 0.0.6
Summary: Summarize pysmoove SV calling VCF results in a BED-like format
Home-page: https://gitlab.com/salk-tm/pysmoove_summary
Author: Anthony Aylward
Author-email: aaylward@salk.edu
Classifier: Programming Language :: Python :: 3
Classifier: License :: OSI Approved :: MIT License
Classifier: Operating System :: OS Independent
License-File: LICENSE
Requires-Dist: pysam
Requires-Dist: pysmoove
